[
  {
    "character_name": "Roll",
    "move_name": "Roll Buster",
    "image": ""
  },
  {
    "character_name": "Roll",
    "move_name": "Weapon Activation",
    "image": ""
  },
  {
    "character_name": "Roll",
    "move_name": "Flowers",
    "image": ""
  },
  {
    "character_name": "Roll",
    "move_name": "Summon Rockball Power-Up",
    "image": ""
  },
  {
    "character_name": "Roll",
    "move_name": "Summon Leaf Shield Power-Up",
    "image": ""
  },
  {
    "character_name": "Roll",
    "move_name": "Summon Tornado Hold Power-Up",
    "image": ""
  },
  {
    "character_name": "Roll",
    "move_name": "Hyper Roll",
    "image": ""
  },
  {
    "character_name": "Roll",
    "move_name": "Beat Plane",
    "image": ""
  },
  {
    "character_name": "Roll",
    "move_name": "Rush Drill",
    "image": ""
  }
]
